qihoo_fpclip_mcp/__init__.py
qihoo_fpclip_mcp/__main__.py
qihoo_fpclip_mcp/embedding_client.py
qihoo_fpclip_mcp/server.py
qihoo_fpclip_mcp/tools.py
qihoo_fgclip_mcp-0.1.2.dist-info/METADATA
qihoo_fgclip_mcp-0.1.2.dist-info/WHEEL
qihoo_fgclip_mcp-0.1.2.dist-info/entry_points.txt
qihoo_fgclip_mcp-0.1.2.dist-info/RECORD
