Metadata-Version: 2.4
Name: qihoo-fgclip-mcp
Version: 0.1.2
Summary: MCP Server for 360 Research embedding services
Project-URL: Homepage, https://github.com/yourusername/qihoo-fgclip-mcp
Project-URL: Repository, https://github.com/yourusername/qihoo-fgclip-mcp
Project-URL: Issues, https://github.com/yourusername/qihoo-fgclip-mcp/issues
Author-email: Your Name <your.email@example.com>
License: MIT
Keywords: 360,ai,embedding,mcp,research
Classifier: Development Status :: 4 - Beta
Classifier: Intended Audience :: Developers
Classifier: License :: OSI Approved :: MIT License
Classifier: Programming Language :: Python :: 3
Classifier: Programming Language :: Python :: 3.10
Classifier: Programming Language :: Python :: 3.11
Classifier: Programming Language :: Python :: 3.12
Classifier: Programming Language :: Python :: 3.13
Classifier: Topic :: Software Development :: Libraries :: Python Modules
Requires-Python: >=3.10
Requires-Dist: httpx>=0.28.1
Requires-Dist: mcp>=1.13.1
Requires-Dist: pip>=25.2
Requires-Dist: pydantic-settings>=2.0.0
Requires-Dist: pydantic>=2.0.0
Requires-Dist: starlette>=0.27.0
Requires-Dist: uvicorn>=0.23.0
